<?xml version="1.0" encoding="utf-8"?>
<doctrine-mapping xmlns="http://doctrine-project.org/schemas/orm/doctrine-mapping" xmlns:xsi="http://www.w3.org/2001/XMLSchema-instance" xsi:schemaLocation="http://doctrine-project.org/schemas/orm/doctrine-mapping http://doctrine-project.org/schemas/orm/doctrine-mapping.xsd">

  <entity name="Application\PortfolioBundle\Entity\Project" table="portfolio_projects">
    <id name="id" type="integer">
      <generator strategy="AUTO"/>
    </id>

    <field name="name" type="string" column="name" length="255"/>
    <field name="description" type="text" column="description"/>

    <many-to-many field="categories" target-entity="Application\PortfolioBundle\Entity\Category">
      <join-table name="portfolio_projects_categories">
        <join-columns>
          <join-column name="project_id" referenced-column-name="id"/>
        </join-columns>
        <inverse-join-columns>
          <join-column name="category_id" referenced-column-name="id"/>
        </inverse-join-columns>
      </join-table>
    </many-to-many>
  </entity>

</doctrine-mapping>
